README.rst
setup.py
aws_syncr/__init__.py
aws_syncr/actions.py
aws_syncr/collector.py
aws_syncr/compat.py
aws_syncr/differ.py
aws_syncr/errors.py
aws_syncr/executor.py
aws_syncr/filename_completer.py
aws_syncr/formatter.py
aws_syncr.egg-info/PKG-INFO
aws_syncr.egg-info/SOURCES.txt
aws_syncr.egg-info/dependency_links.txt
aws_syncr.egg-info/entry_points.txt
aws_syncr.egg-info/requires.txt
aws_syncr.egg-info/top_level.txt
aws_syncr/amazon/__init__.py
aws_syncr/amazon/amazon.py
aws_syncr/amazon/apigateway.py
aws_syncr/amazon/bucket_acls.py
aws_syncr/amazon/common.py
aws_syncr/amazon/iam.py
aws_syncr/amazon/kms.py
aws_syncr/amazon/lambdas.py
aws_syncr/amazon/route53.py
aws_syncr/amazon/s3.py
aws_syncr/option_spec/__init__.py
aws_syncr/option_spec/apigateway.py
aws_syncr/option_spec/aws_syncr_specs.py
aws_syncr/option_spec/buckets.py
aws_syncr/option_spec/documents.py
aws_syncr/option_spec/encryption_keys.py
aws_syncr/option_spec/lambdas.py
aws_syncr/option_spec/resources.py
aws_syncr/option_spec/roles.py
aws_syncr/option_spec/route53.py
aws_syncr/option_spec/statements.py